[{"trip_id":"803","trip_short_name":null},{"trip_id":"801","trip_short_name":null},{"trip_id":"804","trip_short_name":null},{"trip_id":"802","trip_short_name":null},{"trip_id":"323","trip_short_name":null},{"trip_id":"309","trip_short_name":null},{"trip_id":"319","trip_short_name":null},{"trip_id":"329","trip_short_name":null},{"trip_id":"371","trip_short_name":null},{"trip_id":"381","trip_short_name":null},{"trip_id":"375","trip_short_name":null},{"trip_id":"365","trip_short_name":null},{"trip_id":"385","trip_short_name":null},{"trip_id":"305","trip_short_name":null},{"trip_id":"313","trip_short_name":null},{"trip_id":"380","trip_short_name":null},{"trip_id":"370","trip_short_name":null},{"trip_id":"314","trip_short_name":null},{"trip_id":"324","trip_short_name":null},{"trip_id":"366","trip_short_name":null},{"trip_id":"376","trip_short_name":null},{"trip_id":"360","trip_short_name":null},{"trip_id":"330","trip_short_name":null},{"trip_id":"320","trip_short_name":null},{"trip_id":"310","trip_short_name":null},{"trip_id":"386","trip_short_name":null},{"trip_id":"273","trip_short_name":null},{"trip_id":"221","trip_short_name":null},{"trip_id":"215","trip_short_name":null},{"trip_id":"225","trip_short_name":null},{"trip_id":"237","trip_short_name":null},{"trip_id":"257","trip_short_name":null},{"trip_id":"263","trip_short_name":null},{"trip_id":"267","trip_short_name":null},{"trip_id":"269","trip_short_name":null},{"trip_id":"279","trip_short_name":null},{"trip_id":"277","trip_short_name":null},{"trip_id":"283","trip_short_name":null},{"trip_id":"287","trip_short_name":null},{"trip_id":"289","trip_short_name":null},{"trip_id":"233","trip_short_name":null},{"trip_id":"217","trip_short_name":null},{"trip_id":"231","trip_short_name":null},{"trip_id":"207","trip_short_name":null},{"trip_id":"261","trip_short_name":null},{"trip_id":"227","trip_short_name":null},{"trip_id":"211","trip_short_name":null},{"trip_id":"274","trip_short_name":null},{"trip_id":"278","trip_short_name":null},{"trip_id":"282","trip_short_name":null},{"trip_id":"288","trip_short_name":null},{"trip_id":"222","trip_short_name":null},{"trip_id":"216","trip_short_name":null},{"trip_id":"208","trip_short_name":null},{"trip_id":"284","trip_short_name":null},{"trip_id":"258","trip_short_name":null},{"trip_id":"232","trip_short_name":null},{"trip_id":"264","trip_short_name":null},{"trip_id":"226","trip_short_name":null},{"trip_id":"212","trip_short_name":null},{"trip_id":"228","trip_short_name":null},{"trip_id":"218","trip_short_name":null},{"trip_id":"206","trip_short_name":null},{"trip_id":"236","trip_short_name":null},{"trip_id":"254","trip_short_name":null},{"trip_id":"262","trip_short_name":null},{"trip_id":"268","trip_short_name":null},{"trip_id":"272","trip_short_name":null},{"trip_id":"421","trip_short_name":null},{"trip_id":"443","trip_short_name":null},{"trip_id":"444","trip_short_name":null},{"trip_id":"442","trip_short_name":null},{"trip_id":"439","trip_short_name":null},{"trip_id":"441","trip_short_name":null},{"trip_id":"425","trip_short_name":null},{"trip_id":"427","trip_short_name":null},{"trip_id":"435","trip_short_name":null},{"trip_id":"429","trip_short_name":null},{"trip_id":"437","trip_short_name":null},{"trip_id":"433","trip_short_name":null},{"trip_id":"423","trip_short_name":null},{"trip_id":"431","trip_short_name":null},{"trip_id":"434","trip_short_name":null},{"trip_id":"424","trip_short_name":null},{"trip_id":"436","trip_short_name":null},{"trip_id":"426","trip_short_name":null},{"trip_id":"438","trip_short_name":null},{"trip_id":"428","trip_short_name":null},{"trip_id":"440","trip_short_name":null},{"trip_id":"432","trip_short_name":null},{"trip_id":"422","trip_short_name":null},{"trip_id":"430","trip_short_name":null},{"trip_id":"199","trip_short_name":null},{"trip_id":"197","trip_short_name":null},{"trip_id":"195","trip_short_name":null},{"trip_id":"159","trip_short_name":null},{"trip_id":"103","trip_short_name":null},{"trip_id":"151","trip_short_name":null},{"trip_id":"147","trip_short_name":null},{"trip_id":"143","trip_short_name":null},{"trip_id":"139","trip_short_name":null},{"trip_id":"101","trip_short_name":null},{"trip_id":"155","trip_short_name":null},{"trip_id":"135","trip_short_name":null},{"trip_id":"193","trip_short_name":null},{"trip_id":"191","trip_short_name":null},{"trip_id":"150","trip_short_name":null},{"trip_id":"156","trip_short_name":null},{"trip_id":"192","trip_short_name":null},{"trip_id":"194","trip_short_name":null},{"trip_id":"104","trip_short_name":null},{"trip_id":"138","trip_short_name":null},{"trip_id":"142","trip_short_name":null},{"trip_id":"146","trip_short_name":null},{"trip_id":"152","trip_short_name":null},{"trip_id":"102","trip_short_name":null},{"trip_id":"134","trip_short_name":null},{"trip_id":"190","trip_short_name":null},{"trip_id":"196","trip_short_name":null},{"trip_id":"198","trip_short_name":null},{"trip_id":"shuttle431","trip_short_name":null},{"trip_id":"shuttle803","trip_short_name":null},{"trip_id":"shuttle433","trip_short_name":null},{"trip_id":"shuttle423","trip_short_name":null},{"trip_id":"shuttle435","trip_short_name":null},{"trip_id":"shuttle425","trip_short_name":null},{"trip_id":"shuttle437","trip_short_name":null},{"trip_id":"shuttle427","trip_short_name":null},{"trip_id":"shuttle439","trip_short_name":null},{"trip_id":"shuttle441","trip_short_name":null},{"trip_id":"shuttle429","trip_short_name":null},{"trip_id":"shuttle801","trip_short_name":null},{"trip_id":"shuttle430","trip_short_name":null},{"trip_id":"shuttle432","trip_short_name":null},{"trip_id":"shuttle804","trip_short_name":null},{"trip_id":"shuttle422","trip_short_name":null},{"trip_id":"shuttle426","trip_short_name":null},{"trip_id":"shuttle434","trip_short_name":null},{"trip_id":"shuttle424","trip_short_name":null},{"trip_id":"shuttle438","trip_short_name":null},{"trip_id":"shuttle428","trip_short_name":null},{"trip_id":"shuttle802","trip_short_name":null},{"trip_id":"670","trip_short_name":null}]